LICENSE
MANIFEST.in
README.md
setup.py
wechat_utils/__init__.py
wechat_utils.egg-info/PKG-INFO
wechat_utils.egg-info/SOURCES.txt
wechat_utils.egg-info/dependency_links.txt
wechat_utils.egg-info/requires.txt
wechat_utils.egg-info/top_level.txt
wechat_utils/depends_database/__init__.py
wechat_utils/depends_database/init.py
wechat_utils/depends_database/auth/__init__.py
wechat_utils/depends_database/auth/miniapp/__init__.py
wechat_utils/depends_database/auth/miniapp/auth.py
wechat_utils/depends_database/auth/mpapp/__init__.py
wechat_utils/depends_database/auth/mpapp/auth.py
wechat_utils/depends_database/models/__init__.py
wechat_utils/depends_database/models/Mongoengine/__init__.py
wechat_utils/depends_database/models/Mongoengine/_imports_.py
wechat_utils/depends_database/models/Mongoengine/configuration.py
wechat_utils/depends_database/models/Mongoengine/mixin.py
wechat_utils/depends_database/models/Mongoengine/payment.py
wechat_utils/depends_database/models/Mongoengine/user.py
wechat_utils/depends_database/models/Mongoengine/wechat_user.py
wechat_utils/depends_database/models/Sqlalchemy/__init__.py
wechat_utils/depends_database/models/Sqlalchemy/configuration.py
wechat_utils/depends_database/models/Sqlalchemy/user.py
wechat_utils/depends_database/models/Sqlalchemy/wechat_user.py
wechat_utils/depends_database/orm/Mongoengine.py
wechat_utils/depends_database/orm/Sqlalchemy.py
wechat_utils/depends_database/orm/__init__.py
wechat_utils/depends_database/orm/base.py
wechat_utils/depends_database/redis/Redis.py
wechat_utils/depends_database/redis/__init__.py
wechat_utils/depends_database/redis/miniapp/__init__.py
wechat_utils/depends_database/redis/miniapp/redis.py
wechat_utils/depends_database/redis/mpapp/__init__.py
wechat_utils/depends_database/redis/mpapp/redis.py
wechat_utils/depends_database/settings/Mongoengine.py
wechat_utils/depends_database/settings/Sqlalchemy.py
wechat_utils/depends_database/settings/__init__.py
wechat_utils/depends_framework/__init__.py
wechat_utils/depends_framework/django/__init__.py
wechat_utils/depends_framework/django/admin/__init__.py
wechat_utils/depends_framework/django/admin/configuration.py
