Metadata-Version: 2.1
Name: wechat-utils
Version: 2020.7.2.3
Summary: wechat's utils
Home-page: https://github.com/cllen/wechat-utils
Author-email: 13750192465@163.com
License: UNKNOWN
Platform: UNKNOWN
Classifier: Programming Language :: Python :: 3
Classifier: License :: OSI Approved :: MIT License
Classifier: Operating System :: OS Independent
